indexr/__init__.py
indexr/indexr.py
indexr/buildr/__init__.py
indexr/buildr/indexing/BSB.py
indexr/buildr/indexing/__init__.py
indexr/utils/__init__.py
indexr/utils/nlp.py
indexr-1.0.1.dist-info/DESCRIPTION.rst
indexr-1.0.1.dist-info/METADATA
indexr-1.0.1.dist-info/RECORD
indexr-1.0.1.dist-info/WHEEL
indexr-1.0.1.dist-info/metadata.json
indexr-1.0.1.dist-info/top_level.txt
