Metadata-Version: 2.0
Name: indexr
Version: 1.0.1
Summary: A general purpose indexer written in Python.
Home-page: https://github.com/kevin91nl/indexr
Author: Kevin Jacobs
Author-email: kevin91nl@gmail.com
License: ISCL
Keywords: indexr
Platform: UNKNOWN
Classifier: Development Status :: 2 - Pre-Alpha
Classifier: Intended Audience :: Developers
Classifier: License :: OSI Approved :: ISC License (ISCL)
Classifier: Natural Language :: English
Classifier: Programming Language :: Python :: 2
Classifier: Programming Language :: Python :: 2.6
Classifier: Programming Language :: Python :: 2.7
Classifier: Programming Language :: Python :: 3
Classifier: Programming Language :: Python :: 3.3
Classifier: Programming Language :: Python :: 3.4
